{
  "_page.css": {
    "file": "_app/immutable/assets/_page-68aaa35b.css",
    "src": "_page.css"
  },
  "src/routes/+page.ts": {
    "file": "_app/immutable/modules/pages/_page.ts-6a8cdd0a.js",
    "src": "src/routes/+page.ts",
    "isEntry": true,
    "imports": [
      "__page-7e4796dc.js"
    ]
  },
  "_index-95d721c5.js": {
    "file": "_app/immutable/chunks/index-95d721c5.js",
    "isDynamicEntry": true
  },
  "__page-7e4796dc.js": {
    "file": "_app/immutable/chunks/_page-7e4796dc.js"
  },
  "_index-71eac763.js": {
    "file": "_app/immutable/chunks/index-71eac763.js",
    "imports": [
      "_index-d23b2ecc.js"
    ]
  },
  "src/routes/+page.svelte": {
    "file": "_app/immutable/components/pages/_page.svelte-480f6154.js",
    "src": "src/routes/+page.svelte",
    "isEntry": true,
    "imports": [
      "_preload-helper-41c905a7.js",
      "_index-d23b2ecc.js",
      "__page-20446856.js"
    ]
  },
  "node_modules/dompurify/dist/purify.es.js": {
    "file": "_app/immutable/chunks/purify.es-075a2866.js",
    "src": "node_modules/dompurify/dist/purify.es.js",
    "isDynamicEntry": true
  },
  "_preload-helper-41c905a7.js": {
    "file": "_app/immutable/chunks/preload-helper-41c905a7.js"
  },
  ".svelte-kit/generated/nodes/0.js": {
    "file": "_app/immutable/chunks/0-016a1d45.js",
    "src": ".svelte-kit/generated/nodes/0.js",
    "isDynamicEntry": true,
    "imports": [
      "node_modules/@sveltejs/kit/src/runtime/components/layout.svelte"
    ]
  },
  ".svelte-kit/generated/nodes/1.js": {
    "file": "_app/immutable/chunks/1-8d9436e2.js",
    "src": ".svelte-kit/generated/nodes/1.js",
    "isDynamicEntry": true,
    "imports": [
      "node_modules/@sveltejs/kit/src/runtime/components/error.svelte"
    ]
  },
  ".svelte-kit/generated/nodes/2.js": {
    "file": "_app/immutable/chunks/2-b9731ab0.js",
    "src": ".svelte-kit/generated/nodes/2.js",
    "isDynamicEntry": true,
    "imports": [
      "__page-7e4796dc.js",
      "__page-20446856.js"
    ]
  },
  "_singletons-d7293337.js": {
    "file": "_app/immutable/chunks/singletons-d7293337.js",
    "imports": [
      "_index-71eac763.js"
    ]
  },
  "node_modules/@sveltejs/kit/src/runtime/client/start.js": {
    "file": "_app/immutable/start-7e64f86d.js",
    "src": "node_modules/@sveltejs/kit/src/runtime/client/start.js",
    "isEntry": true,
    "imports": [
      "_index-d23b2ecc.js",
      "_singletons-d7293337.js",
      "_preload-helper-41c905a7.js"
    ],
    "dynamicImports": [
      ".svelte-kit/generated/nodes/0.js",
      ".svelte-kit/generated/nodes/1.js",
      ".svelte-kit/generated/nodes/2.js"
    ]
  },
  "node_modules/@sveltejs/kit/src/runtime/components/layout.svelte": {
    "file": "_app/immutable/components/layout.svelte-99529342.js",
    "src": "node_modules/@sveltejs/kit/src/runtime/components/layout.svelte",
    "isEntry": true,
    "imports": [
      "_index-d23b2ecc.js"
    ]
  },
  "node_modules/@sveltejs/kit/src/runtime/components/error.svelte": {
    "file": "_app/immutable/components/error.svelte-1d9f4709.js",
    "src": "node_modules/@sveltejs/kit/src/runtime/components/error.svelte",
    "isEntry": true,
    "imports": [
      "_index-d23b2ecc.js",
      "_singletons-d7293337.js"
    ]
  },
  "_index-d23b2ecc.js": {
    "file": "_app/immutable/chunks/index-d23b2ecc.js"
  },
  "node_modules/canvg/lib/index.es.js": {
    "file": "_app/immutable/chunks/index.es-1ee718b8.js",
    "src": "node_modules/canvg/lib/index.es.js",
    "isDynamicEntry": true,
    "imports": [
      "__page-20446856.js"
    ]
  },
  "node_modules/html2canvas/dist/html2canvas.esm.js": {
    "file": "_app/immutable/chunks/html2canvas.esm-0a33ed42.js",
    "src": "node_modules/html2canvas/dist/html2canvas.esm.js",
    "isDynamicEntry": true
  },
  "__page-20446856.js": {
    "file": "_app/immutable/chunks/_page-20446856.js",
    "imports": [
      "_preload-helper-41c905a7.js",
      "_index-d23b2ecc.js",
      "_index-71eac763.js"
    ],
    "dynamicImports": [
      "node_modules/html2canvas/dist/html2canvas.esm.js",
      "node_modules/dompurify/dist/purify.es.js",
      "node_modules/canvg/lib/index.es.js",
      "_index-95d721c5.js"
    ],
    "css": [
      "_app/immutable/assets/_page-68aaa35b.css"
    ]
  }
}